datasette_leaflet/__init__.py
datasette_leaflet/static/leaflet-v1.7.1.css
datasette_leaflet/static/leaflet-v1.7.1.js
datasette_leaflet/static/leaflet-v1.7.1.min.js
datasette_leaflet/static/images/layers-2x.png
datasette_leaflet/static/images/layers.png
datasette_leaflet/static/images/marker-icon-2x.png
datasette_leaflet/static/images/marker-icon.png
datasette_leaflet/static/images/marker-shadow.png
datasette_leaflet-0.2.2.dist-info/METADATA
datasette_leaflet-0.2.2.dist-info/WHEEL
datasette_leaflet-0.2.2.dist-info/entry_points.txt
datasette_leaflet-0.2.2.dist-info/top_level.txt
datasette_leaflet-0.2.2.dist-info/RECORD
