Metadata-Version: 2.1
Name: datasette-leaflet
Version: 0.2.2
Summary: A plugin that bundles Leaflet.js for Datasette
Home-page: https://github.com/simonw/datasette-leaflet
Author: Simon Willison
License: Apache License, Version 2.0
Project-URL: Issues, https://github.com/simonw/datasette-leaflet/issues
Project-URL: CI, https://github.com/simonw/datasette-leaflet/actions
Project-URL: Changelog, https://github.com/simonw/datasette-leaflet/releases
Platform: UNKNOWN
Requires-Python: >=3.6
Requires-Dist: datasette
Provides-Extra: test
Requires-Dist: pytest ; extra == 'test'
Requires-Dist: pytest-asyncio ; extra == 'test'
